torrent.py
torrent_cli-0.0.9.dist-info/DESCRIPTION.rst
torrent_cli-0.0.9.dist-info/METADATA
torrent_cli-0.0.9.dist-info/RECORD
torrent_cli-0.0.9.dist-info/WHEEL
torrent_cli-0.0.9.dist-info/entry_points.txt
torrent_cli-0.0.9.dist-info/metadata.json
torrent_cli-0.0.9.dist-info/top_level.txt
