Metadata-Version: 2.0
Name: torrent-cli
Version: 0.0.9
Summary: Magnets-Getter CLI Tools
Home-page: https://github.com/chenjiandongx/torrent-cli
Author: chenjiandongx
Author-email: chenjiandongx@qq.com
License: MIT
Platform: UNKNOWN
Requires-Dist: bs4
Requires-Dist: requests
Requires-Dist: lxml
Requires-Dist: future
